bigtesty/__init__.py
bigtesty/dataset_helper.py
bigtesty/definition_test_config_helper.py
bigtesty/definition_test_file_exception.py
bigtesty/files_loader_helper.py
bigtesty/lambda_functions.py
bigtesty/cli/__init__.py
bigtesty/cli/cli_env_vars.py
bigtesty/cli/main.py
bigtesty/given/__init__.py
bigtesty/given/insertion_test_data_bigquery.py
bigtesty/infra/__init__.py
bigtesty/infra/create_iac_for_datasets_with_tables.py
bigtesty/infra/datasets_with_tables_config_file_loader.py
bigtesty/infra/datasets_with_tables_factory.py
bigtesty/infra/infra_input_params.py
bigtesty/infra/launch_tests_ephemeral_infra.py
bigtesty/then/__init__.py
bigtesty/then/assertion_and_tests_reports_result.py
bigtesty/then/assertion_types.py
bigtesty/then/failure_test_exception.py
bigtesty-0.1.1.dist-info/LICENSE
bigtesty-0.1.1.dist-info/METADATA
bigtesty-0.1.1.dist-info/WHEEL
bigtesty-0.1.1.dist-info/entry_points.txt
bigtesty-0.1.1.dist-info/top_level.txt
bigtesty-0.1.1.dist-info/RECORD
