Metadata-Version: 2.1
Name: bigtesty
Version: 0.1.1
Summary: BigTesty is an integration testing framework for BigQuery
Home-page: https://github.com/tosun-si/bigtesty
Author: Mazlum TOSUN
Author-email: mazlum.tosun@gmail.com
License: UNKNOWN
Platform: UNKNOWN
Classifier: License :: OSI Approved :: MIT License
Classifier: Programming Language :: Python :: 3
Classifier: Operating System :: OS Independent
Requires-Python: >=3.9.19
License-File: LICENSE
Requires-Dist: pulumi-gcp ==7.24.0
Requires-Dist: google-cloud-bigquery ==3.23.1
Requires-Dist: google-cloud-storage ==2.17.0
Requires-Dist: typer[all] ==0.12.3
Requires-Dist: pytest ==8.2.1
Requires-Dist: deepdiff ==7.0.1
Requires-Dist: toolz ==0.12.1
